richie/__init__.py
richie/apps/__init__.py
richie/apps/core/__init__.py
richie/apps/core/admin.py
richie/apps/core/cache.py
richie/apps/core/context_processors.py
richie/apps/core/defaults.py
richie/apps/core/factories.py
richie/apps/core/helpers.py
richie/apps/core/models.py
richie/apps/core/fields/__init__.py
richie/apps/core/fields/duration.py
richie/apps/core/fields/effort.py
richie/apps/core/fields/multiselect.py
richie/apps/core/static/richie/favicon/android-chrome-96x96.png
richie/apps/core/static/richie/favicon/apple-touch-icon.png
richie/apps/core/static/richie/favicon/browserconfig.xml
richie/apps/core/static/richie/favicon/favicon-16x16.png
richie/apps/core/static/richie/favicon/favicon-32x32.png
richie/apps/core/static/richie/favicon/favicon.ico
richie/apps/core/static/richie/favicon/mstile-150x150.png
richie/apps/core/static/richie/favicon/safari-pinned-tab.svg
richie/apps/core/static/richie/favicon/site.webmanifest
richie/apps/core/static/richie/fonts/hind/hind-regular.woff
richie/apps/core/static/richie/fonts/hind/hind-regular.woff2
richie/apps/core/static/richie/fonts/hind/hind-semibold.woff
richie/apps/core/static/richie/fonts/hind/hind-semibold.woff2
richie/apps/core/static/richie/fonts/montserrat/montserrat-bold.woff
richie/apps/core/static/richie/fonts/montserrat/montserrat-bold.woff2
richie/apps/core/static/richie/fonts/montserrat/montserrat-extrabold.woff
richie/apps/core/static/richie/fonts/montserrat/montserrat-extrabold.woff2
richie/apps/core/static/richie/fonts/montserrat/montserrat-light.woff
richie/apps/core/static/richie/fonts/montserrat/montserrat-light.woff2
richie/apps/core/static/richie/fonts/montserrat/montserrat-medium.woff
richie/apps/core/static/richie/fonts/montserrat/montserrat-medium.woff2
richie/apps/core/static/richie/images/logo-alt.png
richie/apps/core/static/richie/images/logo.png
richie/apps/core/static/richie/images/components/add-outline.svg
richie/apps/core/static/richie/images/components/arc-white.svg
richie-2.24.1.dist-info/LICENSE
richie-2.24.1.dist-info/METADATA
richie-2.24.1.dist-info/WHEEL
richie-2.24.1.dist-info/top_level.txt
richie-2.24.1.dist-info/zip-safe
richie-2.24.1.dist-info/RECORD
