Metadata-Version: 2.1
Name: richie
Version: 2.24.1
Summary: A CMS to build learning portals for open education
Home-page: https://github.com/openfun/richie
Author: Open FUN (France Universite Numerique)
Author-email: fun.dev@fun-mooc.fr
License: MIT
Keywords: Django,Django-CMS,Open edX
Classifier: Development Status :: 4 - Beta
Classifier: Framework :: Django
Classifier: Framework :: Django :: 1.11
Classifier: Intended Audience :: Developers
Classifier: License :: OSI Approved :: MIT License
Classifier: Natural Language :: English
Classifier: Programming Language :: Python :: 3
Classifier: Programming Language :: Python :: 3.6
License-File: LICENSE
Requires-Dist: arrow
Requires-Dist: Django <4
Requires-Dist: djangocms-file
Requires-Dist: djangocms-googlemap
Requires-Dist: djangocms-link
Requires-Dist: djangocms-picture
Requires-Dist: djangocms-text-ckeditor
Requires-Dist: djangocms-video
Requires-Dist: djangorestframework
Requires-Dist: django-autocomplete-light ==3.9.7
Requires-Dist: django-cms >=3.11.0
Requires-Dist: django-parler >=2.3
Requires-Dist: django-redis >=4.11.0
Requires-Dist: django-treebeard
Requires-Dist: dj-pagination
Requires-Dist: easy-thumbnails[svg] >=2.8
Requires-Dist: elasticsearch <7.0.0,>=6.0.0
Requires-Dist: exrex ==0.11.0
Requires-Dist: oauthlib ==3.2.2
Requires-Dist: requests ==2.31.0
Provides-Extra: ci
Requires-Dist: twine ==4.0.2 ; extra == 'ci'
Provides-Extra: dev
Requires-Dist: bandit ==1.7.5 ; extra == 'dev'
Requires-Dist: black ==23.7.0 ; extra == 'dev'
Requires-Dist: pyRdfa3 ==3.5.3 ; extra == 'dev'
Requires-Dist: cssselect ==1.2.0 ; extra == 'dev'
Requires-Dist: factory-boy ==3.3.0 ; extra == 'dev'
Requires-Dist: flake8 ==6.0.0 ; extra == 'dev'
Requires-Dist: htmlmin ==0.1.12 ; extra == 'dev'
Requires-Dist: ipdb ==0.13.13 ; extra == 'dev'
Requires-Dist: ipython ==8.14.0 ; extra == 'dev'
Requires-Dist: isort ==5.12.0 ; extra == 'dev'
Requires-Dist: lxml ==4.9.3 ; extra == 'dev'
Requires-Dist: msgpack ==1.0.5 ; extra == 'dev'
Requires-Dist: mysqlclient ==2.2.0 ; extra == 'dev'
Requires-Dist: pylint ==2.17.4 ; extra == 'dev'
Requires-Dist: pylint-django ==2.5.3 ; extra == 'dev'
Requires-Dist: pytest ==7.4.0 ; extra == 'dev'
Requires-Dist: pytest-cov ==4.1.0 ; extra == 'dev'
Requires-Dist: pytest-django ==4.5.2 ; extra == 'dev'
Requires-Dist: responses ==0.23.1 ; extra == 'dev'
Provides-Extra: sandbox
Requires-Dist: django-configurations ==2.4.1 ; extra == 'sandbox'
Requires-Dist: dockerflow ==2022.8.0 ; extra == 'sandbox'
Requires-Dist: factory-boy ==3.3.0 ; extra == 'sandbox'
Requires-Dist: gunicorn ==21.2.0 ; extra == 'sandbox'
Requires-Dist: psycopg2-binary ==2.9.6 ; extra == 'sandbox'
Requires-Dist: sentry-sdk ==1.28.1 ; extra == 'sandbox'
